githack/__init__.py
githack/__main__.py
githack/scanner.py
githack/parse/__init__.py
githack/parse/parse.py
githack/parse/structure.py
githack/useragents/__init__.py
githack/useragents/data.py
githack-0.0.4.post1.dist-info/LICENSE
githack-0.0.4.post1.dist-info/METADATA
githack-0.0.4.post1.dist-info/WHEEL
githack-0.0.4.post1.dist-info/entry_points.txt
githack-0.0.4.post1.dist-info/top_level.txt
githack-0.0.4.post1.dist-info/RECORD
