Metadata-Version: 2.1
Name: githack
Version: 0.0.4.post1
Summary: A pure python implemented .git/ folder disclosure exploit
Home-page: https://github.com/OwenChia/githack
Author: Owen Chia
License: UNKNOWN
Keywords: git web-security leakage
Platform: UNKNOWN
Classifier: Development Status :: 3 - Alpha
Classifier: Environment :: Console
Classifier: License :: OSI Approved :: GNU General Public License v3 (GPLv3)
Classifier: Programming Language :: Python :: 3
Classifier: Programming Language :: Python :: 3.6
Classifier: Programming Language :: Python :: 3.7
Classifier: Programming Language :: Python :: Implementation :: CPython
Requires-Python: >=3.6
